rfid_reader/__init__.py
rfid_reader/exceptions.py
rfid_reader/reader.py
uhf_rfid_reader_sdk-0.0.0.dist-info/LICENCE
uhf_rfid_reader_sdk-0.0.0.dist-info/METADATA
uhf_rfid_reader_sdk-0.0.0.dist-info/WHEEL
uhf_rfid_reader_sdk-0.0.0.dist-info/top_level.txt
uhf_rfid_reader_sdk-0.0.0.dist-info/RECORD
